pynedra/__init__.py
pynedra/options.py
pynedra/uri.py
pynedra/web_service.py
pynedra-0.1.6.dist-info/WHEEL
pynedra-0.1.6.dist-info/METADATA
pynedra-0.1.6.dist-info/RECORD
